LICENSE.txt
MANIFEST.in
README.rst
setup.py
prestaorm/__init__.py
prestaorm/bases.py
prestaorm/managers.py
prestaorm/mixins.py
prestaorm/models.py
prestaorm/service.py
prestaorm/utils.py
prestaorm.egg-info/PKG-INFO
prestaorm.egg-info/SOURCES.txt
prestaorm.egg-info/dependency_links.txt
prestaorm.egg-info/top_level.txt