Metadata-Version: 1.1
Name: prestaorm
Version: 0.0.4
Summary: Access to prestashop API using django similar ORM Syntax
Home-page: https://github.com/josesanch/prestaorm
Author: José Sánchez Moreno
Author-email: jose@o2w.es
License: MIT
Platform: All platforms
Classifier: Development Status :: 4 - Beta
Classifier: Intended Audience :: Developers
Classifier: License :: OSI Approved :: Python Software Foundation License
Classifier: Operating System :: MacOS :: MacOS X
Classifier: Operating System :: Microsoft :: Windows
Classifier: Operating System :: POSIX
Classifier: Programming Language :: Python
